adfotg/__init__.py
adfotg/api.py
adfotg/apidoc.py
adfotg/apiutil.py
adfotg/cli.py
adfotg/config.py
adfotg/error.py
adfotg/os_install.py
adfotg/server.py
adfotg/storage.py
adfotg/util.py
adfotg/version.py
adfotg/adf/__init__.py
adfotg/adf/api.py
adfotg/amitools/__init__.py
adfotg/amitools/fs/ADFSBitmap.py
adfotg/amitools/fs/ADFSDir.py
adfotg/amitools/fs/ADFSFile.py
adfotg/amitools/fs/ADFSNode.py
adfotg/amitools/fs/ADFSVolDir.py
adfotg/amitools/fs/ADFSVolume.py
adfotg/amitools/fs/DosType.py
adfotg/amitools/fs/FSError.py
adfotg/amitools/fs/FSString.py
adfotg/amitools/fs/FileName.py
adfotg/amitools/fs/Imager.py
adfotg/amitools/fs/MetaDB.py
adfotg/amitools/fs/MetaInfo.py
adfotg/amitools/fs/MetaInfoFSUAE.py
adfotg/amitools/fs/ProtectFlags.py
adfotg/amitools/fs/Repacker.py
adfotg/amitools/fs/RootMetaInfo.py
adfotg/amitools/fs/TimeStamp.py
adfotg/amitools/fs/__init__.py
adfotg/amitools/fs/blkdev/ADFBlockDevice.py
adfotg/amitools/fs/blkdev/BlkDevFactory.py
adfotg/amitools/fs/blkdev/BlockDevice.py
adfotg/amitools/fs/blkdev/DiskGeometry.py
adfotg/amitools/fs/blkdev/HDFBlockDevice.py
adfotg/amitools/fs/blkdev/ImageFile.py
adfotg/amitools/fs/blkdev/PartBlockDevice.py
adfotg/amitools/fs/blkdev/RawBlockDevice.py
adfotg/amitools/fs/blkdev/__init__.py
adfotg/amitools/fs/block/BitmapBlock.py
adfotg/amitools/fs/block/BitmapExtBlock.py
adfotg/amitools/fs/block/Block.py
adfotg/amitools/fs/block/BootBlock.py
adfotg/amitools/fs/block/CommentBlock.py
adfotg/amitools/fs/block/DirCacheBlock.py
adfotg/amitools/fs/block/EntryBlock.py
adfotg/amitools/fs/block/FileDataBlock.py
adfotg/amitools/fs/block/FileHeaderBlock.py
adfotg/amitools/fs/block/FileListBlock.py
adfotg/amitools/fs/block/RootBlock.py
adfotg/amitools/fs/block/UserDirBlock.py
adfotg/amitools/fs/block/__init__.py
adfotg/amitools/fs/block/bootcode/boot1x.bin
adfotg/amitools/fs/block/bootcode/boot2x3x.bin
adfotg/amitools/fs/block/rdb/BadBlocksBlock.py
adfotg/amitools/fs/block/rdb/FSHeaderBlock.py
adfotg-0.4.0.dist-info/LICENSE
adfotg-0.4.0.dist-info/METADATA
adfotg-0.4.0.dist-info/WHEEL
adfotg-0.4.0.dist-info/entry_points.txt
adfotg-0.4.0.dist-info/top_level.txt
adfotg-0.4.0.dist-info/RECORD
