Metadata-Version: 2.1
Name: adfotg
Version: 0.4.0
Summary: ADF On-The-Go - convert your RPi Zero to Gotek-ready USB disk
Author-email: Robikz <zalewapl@gmail.com>
License: MIT License
Project-URL: Homepage, https://github.com/zalewa/adfotg
Keywords: Amiga,Gotek,Raspberry Pi
Requires-Python: >=3.8
License-File: LICENSE
Requires-Dist: Flask ==2.1.*
Requires-Dist: werkzeug ~=2.0
Requires-Dist: importlib-metadata <7.0,>=3.0 ; python_version < "3.8.1"
